odoo/addons/shopinvader_customer_activity/README.rst
odoo/addons/shopinvader_customer_activity/__init__.py
odoo/addons/shopinvader_customer_activity/__manifest__.py
odoo/addons/shopinvader_customer_activity/i18n/shopinvader_customer_activity.pot
odoo/addons/shopinvader_customer_activity/models/__init__.py
odoo/addons/shopinvader_customer_activity/models/shopinvader_partner.py
odoo/addons/shopinvader_customer_activity/readme/CONTRIBUTORS.rst
odoo/addons/shopinvader_customer_activity/readme/DESCRIPTION.rst
odoo/addons/shopinvader_customer_activity/readme/ROADMAP.rst
odoo/addons/shopinvader_customer_activity/services/__init__.py
odoo/addons/shopinvader_customer_activity/services/service.py
odoo/addons/shopinvader_customer_activity/static/description/index.html
odoo/addons/shopinvader_customer_activity/tests/__init__.py
odoo/addons/shopinvader_customer_activity/tests/test_service.py
odoo/addons/shopinvader_customer_activity/views/res_partner.xml
odoo/addons/shopinvader_customer_activity/views/shopinvader_partner.xml
odoo14_addon_shopinvader_customer_activity-14.0.1.0.1.dist-info/METADATA
odoo14_addon_shopinvader_customer_activity-14.0.1.0.1.dist-info/WHEEL
odoo14_addon_shopinvader_customer_activity-14.0.1.0.1.dist-info/top_level.txt
odoo14_addon_shopinvader_customer_activity-14.0.1.0.1.dist-info/RECORD
